pytest_emoji/__init__.py
pytest_emoji/hooks.py
pytest_emoji/plugin.py
pytest_emoji-0.2.0.dist-info/LICENSE
pytest_emoji-0.2.0.dist-info/METADATA
pytest_emoji-0.2.0.dist-info/WHEEL
pytest_emoji-0.2.0.dist-info/entry_points.txt
pytest_emoji-0.2.0.dist-info/top_level.txt
pytest_emoji-0.2.0.dist-info/RECORD
